{
  "experiment": "dishbrain_replication",
  "scale": "small",
  "device": "cpu",
  "n_runs": 5,
  "base_seed": 42,
  "total_time_s": 822.85,
  "system": {
    "platform": "macOS-15.5-arm64-arm-64bit-Mach-O",
    "python": "3.14.2",
    "torch": "2.10.0",
    "backend": "mps",
    "gpu": "Apple Silicon (MPS)"
  },
  "runs": [
    {
      "seed": 42,
      "experiments": {
        "6": {
          "passed": false,
          "time": 169.150132,
          "train_rallies": 60,
          "test_rallies": 20,
          "best_signal": "free_energy",
          "results": {
            "free_energy": {
              "train_total": 25,
              "train_rate": 0.416667,
              "train_last10": 0.6,
              "test_total": 9,
              "test_rate": 0.45,
              "test_last10": 0.5,
              "train_outcomes": [
                0,
                0,
                0,
                1,
                0,
                0,
                1,
                0,
                0,
                1,
                1,
                0,
                1,
                0,
                1,
                1,
                1,
                0,
                0,
                0,
                1,
                0,
                0,
                1,
                1,
                0,
                1,
                0,
                0,
                0,
                0,
                1,
                1,
                1,
                0,
                0,
                1,
                0,
                0,
                1,
                1,
                1,
                0,
                0,
                0,
                0,
                0,
                0,
                0,
                0,
                1,
                0,
                0,
                1,
                0,
                1,
                0,
                1,
                1,
                1
              ],
              "test_outcomes": [
                0,
                1,
                0,
                0,
                1,
                0,
                1,
                1,
                0,
                0,
                1,
                1,
                1,
                0,
                0,
                1,
                0,
                1,
                0,
                0
              ]
            },
            "free_energy_balanced": {
              "train_total": 28,
              "train_rate": 0.466667,
              "train_last10": 0.5,
              "test_total": 8,
              "test_rate": 0.4,
              "test_last10": 0.3,
              "train_outcomes": [
                0,
                1,
                0,
                1,
                0,
                0,
                1,
                0,
                0,
                1,
                1,
                0,
                1,
                0,
                1,
                1,
                1,
                0,
                1,
                0,
                0,
                0,
                0,
                1,
                1,
                1,
                1,
                0,
                0,
                0,
                1,
                0,
                1,
                1,
                0,
                0,
                1,
                0,
                0,
                0,
                1,
                1,
                0,
                1,
                0,
                0,
                1,
                0,
                1,
                0,
                1,
                0,
                0,
                0,
                0,
                1,
                0,
                1,
                1,
                1
              ],
              "test_outcomes": [
                0,
                1,
                0,
                1,
                1,
                0,
                0,
                0,
                1,
                1,
                0,
                1,
                0,
                0,
                1,
                0,
                0,
                0,
                0,
                1
              ]
            },
            "free_energy_replay": {
              "train_total": 24,
              "train_rate": 0.4,
              "train_last10": 0.2,
              "test_total": 7,
              "test_rate": 0.35,
              "test_last10": 0.4,
              "train_outcomes": [
                0,
                0,
                0,
                1,
                1,
                0,
                0,
                1,
                0,
                0,
                1,
                0,
                0,
                1,
                0,
                1,
                0,
                0,
                1,
                0,
                0,
                0,
                1,
                1,
                1,
                0,
                1,
                0,
                0,
                0,
                1,
                1,
                1,
                1,
                0,
                0,
                1,
                0,
                1,
                1,
                1,
                1,
                0,
                0,
                0,
                1,
                0,
                0,
                1,
                0,
                0,
                0,
                0,
                1,
                0,
                1,
                0,
                0,
                0,
                0
              ],
              "test_outcomes": [
                0,
                0,
                0,
                0,
                0,
                0,
                0,
                1,
                1,
                1,
                1,
                1,
                1,
                0,
                0,
                0,
                0,
                1,
                0,
                0
              ]
            },
            "free_energy_corrective": {
              "train_total": 25,
              "train_rate": 0.416667,
              "train_last10": 0.6,
              "test_total": 9,
              "test_rate": 0.45,
              "test_last10": 0.5,
              "train_outcomes": [
                0,
                1,
                0,
                1,
                0,
                0,
                1,
                0,
                0,
                1,
                1,
                0,
                0,
                0,
                0,
                1,
                1,
                0,
                1,
                0,
                0,
                0,
                0,
                0,
                1,
                0,
                1,
                0,
                0,
                1,
                1,
                0,
                1,
                1,
                0,
                0,
                0,
                0,
                1,
                1,
                1,
                1,
                0,
                0,
                0,
                0,
                0,
                1,
                0,
                0,
                1,
                0,
                0,
                1,
                0,
                1,
                0,
                1,
                1,
                1
              ],
              "test_outcomes": [
                0,
                1,
                0,
                0,
                1,
                0,
                1,
                0,
                1,
                0,
                1,
                1,
                1,
                0,
                1,
                0,
                0,
                1,
                0,
                0
              ]
            },
            "da_reward": {
              "train_total": 19,
              "train_rate": 0.316667,
              "train_last10": 0.6,
              "test_total": 9,
              "test_rate": 0.45,
              "test_last10": 0.4,
              "train_outcomes": [
                0,
                1,
                0,
                1,
                0,
                0,
                1,
                0,
                0,
                1,
                1,
                0,
                0,
                0,
                0,
                1,
                0,
                0,
                1,
                0,
                0,
                0,
                0,
                1,
                0,
                0,
                0,
                0,
                0,
                0,
                0,
                0,
                0,
                1,
                0,
                0,
                1,
                0,
                1,
                0,
                1,
                1,
                0,
                0,
                0,
                0,
                0,
                0,
                0,
                0,
                1,
                0,
                0,
                1,
                0,
                1,
                0,
                1,
                1,
                1
              ],
              "test_outcomes": [
                0,
                1,
                0,
                0,
                1,
                0,
                1,
                1,
                0,
                1,
                0,
                0,
                1,
                0,
                1,
                0,
                0,
                1,
                0,
                1
              ]
            },
            "random": {
              "train_total": 29,
              "train_rate": 0.483333,
              "train_last10": 0.6,
              "test_total": 6,
              "test_rate": 0.3,
              "test_last10": 0.3,
              "train_outcomes": [
                0,
                1,
                0,
                1,
                0,
                0,
                1,
                1,
                0,
                1,
                1,
                0,
                1,
                1,
                0,
                1,
                1,
                0,
                0,
                0,
                1,
                0,
                0,
                0,
                0,
                1,
                0,
                0,
                0,
                1,
                1,
                0,
                1,
                1,
                0,
                1,
                1,
                0,
                0,
                1,
                1,
                1,
                1,
                0,
                0,
                1,
                0,
                0,
                0,
                0,
                1,
                0,
                1,
                1,
                0,
                1,
                1,
                0,
                0,
                1
              ],
              "test_outcomes": [
                0,
                0,
                0,
                0,
                0,
                0,
                1,
                1,
                1,
                0,
                0,
                1,
                0,
                0,
                1,
                0,
                0,
                1,
                0,
                0
              ]
            }
          },
          "name": "Pong Signal Optimization"
        }
      }
    },
    {
      "seed": 43,
      "experiments": {
        "6": {
          "passed": true,
          "time": 179.785655,
          "train_rallies": 60,
          "test_rallies": 20,
          "best_signal": "free_energy_balanced",
          "results": {
            "free_energy": {
              "train_total": 33,
              "train_rate": 0.55,
              "train_last10": 0.6,
              "test_total": 7,
              "test_rate": 0.35,
              "test_last10": 0.2,
              "train_outcomes": [
                1,
                1,
                1,
                0,
                1,
                1,
                1,
                0,
                1,
                1,
                1,
                1,
                1,
                0,
                0,
                1,
                0,
                1,
                1,
                1,
                0,
                1,
                0,
                0,
                1,
                0,
                0,
                0,
                1,
                0,
                0,
                1,
                0,
                0,
                0,
                1,
                0,
                0,
                1,
                0,
                0,
                1,
                1,
                0,
                0,
                0,
                1,
                1,
                1,
                1,
                1,
                0,
                0,
                0,
                1,
                1,
                1,
                0,
                1,
                1
              ],
              "test_outcomes": [
                1,
                0,
                1,
                0,
                0,
                0,
                1,
                1,
                1,
                0,
                0,
                1,
                0,
                0,
                0,
                0,
                0,
                0,
                1,
                0
              ]
            },
            "free_energy_balanced": {
              "train_total": 38,
              "train_rate": 0.633333,
              "train_last10": 0.7,
              "test_total": 10,
              "test_rate": 0.5,
              "test_last10": 0.4,
              "train_outcomes": [
                1,
                1,
                1,
                0,
                1,
                1,
                1,
                0,
                1,
                1,
                1,
                1,
                1,
                0,
                0,
                1,
                0,
                1,
                1,
                1,
                0,
                1,
                0,
                0,
                1,
                0,
                0,
                1,
                1,
                0,
                1,
                1,
                0,
                0,
                0,
                1,
                0,
                0,
                1,
                0,
                1,
                1,
                1,
                0,
                0,
                1,
                1,
                1,
                1,
                1,
                1,
                0,
                0,
                0,
                1,
                1,
                1,
                1,
                1,
                1
              ],
              "test_outcomes": [
                1,
                0,
                1,
                0,
                0,
                1,
                0,
                1,
                1,
                1,
                0,
                1,
                0,
                1,
                0,
                0,
                0,
                1,
                0,
                1
              ]
            },
            "free_energy_replay": {
              "train_total": 32,
              "train_rate": 0.533333,
              "train_last10": 0.5,
              "test_total": 8,
              "test_rate": 0.4,
              "test_last10": 0.4,
              "train_outcomes": [
                1,
                1,
                1,
                0,
                1,
                1,
                1,
                0,
                1,
                1,
                1,
                1,
                1,
                0,
                0,
                1,
                0,
                1,
                1,
                1,
                0,
                1,
                0,
                0,
                1,
                0,
                0,
                0,
                0,
                1,
                0,
                0,
                0,
                1,
                0,
                1,
                0,
                0,
                0,
                1,
                1,
                1,
                1,
                0,
                1,
                0,
                0,
                0,
                1,
                1,
                1,
                0,
                1,
                0,
                1,
                0,
                0,
                0,
                1,
                1
              ],
              "test_outcomes": [
                1,
                0,
                0,
                0,
                0,
                0,
                1,
                1,
                1,
                0,
                1,
                0,
                0,
                0,
                1,
                0,
                1,
                0,
                1,
                0
              ]
            },
            "free_energy_corrective": {
              "train_total": 31,
              "train_rate": 0.516667,
              "train_last10": 0.4,
              "test_total": 9,
              "test_rate": 0.45,
              "test_last10": 0.4,
              "train_outcomes": [
                1,
                1,
                1,
                0,
                1,
                1,
                1,
                0,
                1,
                1,
                1,
                1,
                1,
                0,
                0,
                1,
                0,
                1,
                1,
                1,
                0,
                0,
                0,
                0,
                1,
                0,
                0,
                1,
                1,
                0,
                0,
                1,
                0,
                0,
                0,
                1,
                0,
                0,
                1,
                0,
                0,
                1,
                1,
                0,
                0,
                0,
                1,
                1,
                1,
                1,
                1,
                0,
                0,
                0,
                0,
                0,
                1,
                0,
                1,
                1
              ],
              "test_outcomes": [
                1,
                0,
                0,
                1,
                1,
                0,
                0,
                0,
                1,
                1,
                1,
                0,
                1,
                0,
                0,
                0,
                0,
                0,
                1,
                1
              ]
            },
            "da_reward": {
              "train_total": 34,
              "train_rate": 0.566667,
              "train_last10": 0.7,
              "test_total": 9,
              "test_rate": 0.45,
              "test_last10": 0.3,
              "train_outcomes": [
                1,
                1,
                1,
                0,
                0,
                1,
                1,
                1,
                1,
                1,
                1,
                1,
                1,
                0,
                1,
                0,
                0,
                1,
                1,
                1,
                0,
                1,
                0,
                0,
                1,
                0,
                0,
                1,
                0,
                0,
                1,
                0,
                0,
                1,
                0,
                1,
                0,
                0,
                1,
                0,
                1,
                1,
                1,
                0,
                1,
                0,
                0,
                0,
                1,
                0,
                1,
                0,
                1,
                0,
                1,
                0,
                1,
                1,
                1,
                1
              ],
              "test_outcomes": [
                1,
                0,
                0,
                0,
                1,
                1,
                1,
                1,
                0,
                1,
                1,
                1,
                0,
                0,
                0,
                0,
                0,
                1,
                0,
                0
              ]
            },
            "random": {
              "train_total": 27,
              "train_rate": 0.45,
              "train_last10": 0.4,
              "test_total": 7,
              "test_rate": 0.35,
              "test_last10": 0.3,
              "train_outcomes": [
                1,
                1,
                0,
                1,
                0,
                0,
                0,
                0,
                1,
                1,
                1,
                1,
                1,
                0,
                0,
                0,
                0,
                1,
                1,
                1,
                0,
                0,
                1,
                0,
                1,
                1,
                0,
                0,
                1,
                0,
                0,
                1,
                0,
                0,
                0,
                0,
                0,
                0,
                1,
                1,
                1,
                1,
                0,
                0,
                0,
                0,
                1,
                0,
                1,
                1,
                1,
                1,
                0,
                0,
                1,
                0,
                0,
                0,
                0,
                1
              ],
              "test_outcomes": [
                0,
                0,
                1,
                0,
                0,
                1,
                0,
                0,
                1,
                1,
                1,
                0,
                1,
                0,
                0,
                0,
                0,
                0,
                0,
                1
              ]
            }
          },
          "name": "Pong Signal Optimization"
        }
      }
    },
    {
      "seed": 44,
      "experiments": {
        "6": {
          "passed": true,
          "time": 160.001361,
          "train_rallies": 60,
          "test_rallies": 20,
          "best_signal": "da_reward",
          "results": {
            "free_energy": {
              "train_total": 33,
              "train_rate": 0.55,
              "train_last10": 0.7,
              "test_total": 9,
              "test_rate": 0.45,
              "test_last10": 0.5,
              "train_outcomes": [
                1,
                1,
                0,
                0,
                0,
                1,
                0,
                0,
                1,
                0,
                0,
                1,
                0,
                1,
                1,
                1,
                1,
                1,
                1,
                1,
                1,
                1,
                1,
                1,
                0,
                0,
                0,
                0,
                1,
                0,
                1,
                0,
                0,
                1,
                1,
                0,
                0,
                0,
                0,
                1,
                0,
                0,
                0,
                0,
                1,
                1,
                1,
                1,
                1,
                0,
                1,
                0,
                1,
                0,
                1,
                1,
                1,
                1,
                1,
                0
              ],
              "test_outcomes": [
                0,
                1,
                0,
                0,
                1,
                0,
                0,
                1,
                0,
                1,
                0,
                0,
                0,
                1,
                1,
                1,
                1,
                1,
                0,
                0
              ]
            },
            "free_energy_balanced": {
              "train_total": 34,
              "train_rate": 0.566667,
              "train_last10": 0.4,
              "test_total": 8,
              "test_rate": 0.4,
              "test_last10": 0.4,
              "train_outcomes": [
                1,
                1,
                0,
                0,
                0,
                1,
                0,
                0,
                0,
                1,
                0,
                1,
                0,
                1,
                1,
                1,
                1,
                1,
                1,
                1,
                1,
                1,
                1,
                1,
                1,
                0,
                0,
                0,
                1,
                0,
                1,
                1,
                0,
                1,
                1,
                0,
                0,
                0,
                0,
                0,
                1,
                0,
                1,
                1,
                1,
                1,
                1,
                1,
                1,
                0,
                0,
                1,
                1,
                0,
                0,
                1,
                0,
                0,
                1,
                0
              ],
              "test_outcomes": [
                1,
                0,
                0,
                0,
                1,
                0,
                1,
                1,
                0,
                0,
                0,
                0,
                1,
                1,
                1,
                0,
                0,
                1,
                0,
                0
              ]
            },
            "free_energy_replay": {
              "train_total": 29,
              "train_rate": 0.483333,
              "train_last10": 0.4,
              "test_total": 6,
              "test_rate": 0.3,
              "test_last10": 0.2,
              "train_outcomes": [
                1,
                0,
                1,
                0,
                0,
                0,
                0,
                0,
                1,
                0,
                0,
                1,
                0,
                1,
                1,
                0,
                1,
                1,
                1,
                0,
                0,
                1,
                1,
                0,
                1,
                0,
                1,
                0,
                1,
                0,
                1,
                1,
                0,
                0,
                1,
                0,
                0,
                1,
                1,
                0,
                0,
                0,
                0,
                1,
                1,
                1,
                1,
                1,
                1,
                0,
                0,
                1,
                1,
                0,
                0,
                1,
                1,
                0,
                0,
                0
              ],
              "test_outcomes": [
                0,
                1,
                0,
                0,
                1,
                0,
                1,
                0,
                0,
                1,
                0,
                0,
                0,
                1,
                0,
                0,
                0,
                0,
                1,
                0
              ]
            },
            "free_energy_corrective": {
              "train_total": 31,
              "train_rate": 0.516667,
              "train_last10": 0.0,
              "test_total": 8,
              "test_rate": 0.4,
              "test_last10": 0.5,
              "train_outcomes": [
                1,
                0,
                1,
                0,
                0,
                1,
                0,
                0,
                1,
                0,
                0,
                1,
                0,
                1,
                1,
                1,
                1,
                1,
                1,
                1,
                1,
                1,
                0,
                1,
                1,
                0,
                0,
                0,
                1,
                0,
                1,
                0,
                1,
                1,
                1,
                0,
                1,
                0,
                1,
                0,
                1,
                0,
                1,
                1,
                1,
                1,
                1,
                1,
                1,
                0,
                0,
                0,
                0,
                0,
                0,
                0,
                0,
                0,
                0,
                0
              ],
              "test_outcomes": [
                0,
                1,
                0,
                0,
                0,
                0,
                0,
                1,
                0,
                1,
                0,
                0,
                0,
                0,
                1,
                1,
                1,
                1,
                0,
                1
              ]
            },
            "da_reward": {
              "train_total": 30,
              "train_rate": 0.5,
              "train_last10": 0.4,
              "test_total": 10,
              "test_rate": 0.5,
              "test_last10": 0.6,
              "train_outcomes": [
                1,
                1,
                0,
                1,
                0,
                0,
                0,
                0,
                1,
                0,
                0,
                1,
                0,
                1,
                0,
                0,
                1,
                1,
                1,
                1,
                0,
                1,
                1,
                1,
                1,
                0,
                0,
                0,
                0,
                0,
                1,
                0,
                1,
                1,
                0,
                0,
                0,
                1,
                1,
                1,
                1,
                1,
                0,
                0,
                0,
                1,
                1,
                1,
                1,
                0,
                0,
                0,
                1,
                0,
                1,
                1,
                0,
                0,
                0,
                1
              ],
              "test_outcomes": [
                0,
                1,
                1,
                0,
                1,
                0,
                0,
                1,
                0,
                0,
                0,
                1,
                0,
                1,
                1,
                1,
                1,
                1,
                0,
                0
              ]
            },
            "random": {
              "train_total": 32,
              "train_rate": 0.533333,
              "train_last10": 0.5,
              "test_total": 8,
              "test_rate": 0.4,
              "test_last10": 0.6,
              "train_outcomes": [
                1,
                0,
                1,
                0,
                0,
                1,
                0,
                0,
                1,
                0,
                0,
                1,
                0,
                1,
                1,
                1,
                1,
                0,
                1,
                1,
                0,
                1,
                1,
                1,
                0,
                0,
                1,
                0,
                1,
                0,
                0,
                0,
                1,
                1,
                0,
                0,
                1,
                1,
                0,
                0,
                1,
                1,
                0,
                1,
                0,
                1,
                1,
                1,
                1,
                0,
                0,
                1,
                0,
                0,
                1,
                1,
                1,
                1,
                0,
                0
              ],
              "test_outcomes": [
                0,
                1,
                0,
                0,
                0,
                0,
                0,
                1,
                0,
                0,
                0,
                0,
                1,
                1,
                1,
                1,
                1,
                1,
                0,
                0
              ]
            }
          },
          "name": "Pong Signal Optimization"
        }
      }
    },
    {
      "seed": 45,
      "experiments": {
        "6": {
          "passed": true,
          "time": 167.248188,
          "train_rallies": 60,
          "test_rallies": 20,
          "best_signal": "da_reward",
          "results": {
            "free_energy": {
              "train_total": 26,
              "train_rate": 0.433333,
              "train_last10": 0.3,
              "test_total": 10,
              "test_rate": 0.5,
              "test_last10": 0.3,
              "train_outcomes": [
                0,
                0,
                1,
                0,
                0,
                0,
                0,
                0,
                0,
                1,
                0,
                1,
                0,
                0,
                1,
                1,
                0,
                1,
                1,
                0,
                1,
                0,
                1,
                1,
                1,
                0,
                1,
                0,
                1,
                1,
                0,
                0,
                0,
                1,
                1,
                1,
                1,
                1,
                0,
                0,
                0,
                1,
                0,
                0,
                0,
                0,
                1,
                0,
                1,
                1,
                0,
                0,
                0,
                0,
                0,
                1,
                1,
                0,
                0,
                1
              ],
              "test_outcomes": [
                0,
                0,
                0,
                1,
                1,
                1,
                1,
                1,
                1,
                1,
                0,
                1,
                0,
                0,
                0,
                0,
                1,
                1,
                0,
                0
              ]
            },
            "free_energy_balanced": {
              "train_total": 22,
              "train_rate": 0.366667,
              "train_last10": 0.2,
              "test_total": 10,
              "test_rate": 0.5,
              "test_last10": 0.5,
              "train_outcomes": [
                0,
                0,
                1,
                0,
                0,
                0,
                0,
                0,
                0,
                1,
                1,
                1,
                0,
                0,
                1,
                1,
                0,
                1,
                1,
                0,
                1,
                0,
                0,
                0,
                0,
                1,
                0,
                0,
                1,
                1,
                0,
                0,
                0,
                0,
                0,
                1,
                1,
                1,
                0,
                0,
                1,
                1,
                0,
                0,
                0,
                0,
                0,
                1,
                1,
                1,
                0,
                0,
                0,
                0,
                0,
                1,
                1,
                0,
                0,
                0
              ],
              "test_outcomes": [
                1,
                0,
                0,
                1,
                1,
                1,
                0,
                0,
                0,
                1,
                0,
                1,
                0,
                1,
                0,
                0,
                1,
                1,
                0,
                1
              ]
            },
            "free_energy_replay": {
              "train_total": 25,
              "train_rate": 0.416667,
              "train_last10": 0.4,
              "test_total": 10,
              "test_rate": 0.5,
              "test_last10": 0.5,
              "train_outcomes": [
                0,
                0,
                1,
                0,
                0,
                1,
                0,
                0,
                1,
                1,
                0,
                1,
                0,
                0,
                0,
                0,
                0,
                0,
                1,
                0,
                1,
                0,
                1,
                0,
                0,
                1,
                0,
                0,
                1,
                1,
                1,
                0,
                0,
                1,
                0,
                1,
                1,
                1,
                1,
                0,
                0,
                1,
                0,
                1,
                0,
                0,
                0,
                0,
                1,
                1,
                0,
                0,
                1,
                0,
                0,
                1,
                1,
                1,
                0,
                0
              ],
              "test_outcomes": [
                0,
                0,
                1,
                0,
                1,
                1,
                1,
                1,
                0,
                0,
                1,
                1,
                0,
                0,
                1,
                0,
                1,
                0,
                0,
                1
              ]
            },
            "free_energy_corrective": {
              "train_total": 25,
              "train_rate": 0.416667,
              "train_last10": 0.4,
              "test_total": 9,
              "test_rate": 0.45,
              "test_last10": 0.3,
              "train_outcomes": [
                0,
                1,
                1,
                0,
                0,
                0,
                0,
                0,
                0,
                0,
                0,
                1,
                0,
                1,
                1,
                1,
                0,
                1,
                0,
                1,
                1,
                0,
                0,
                1,
                0,
                1,
                0,
                0,
                1,
                1,
                0,
                0,
                0,
                0,
                1,
                1,
                1,
                0,
                1,
                0,
                0,
                1,
                0,
                0,
                0,
                0,
                1,
                0,
                1,
                1,
                0,
                0,
                1,
                0,
                0,
                0,
                1,
                0,
                1,
                1
              ],
              "test_outcomes": [
                0,
                1,
                0,
                1,
                0,
                1,
                1,
                1,
                0,
                1,
                0,
                0,
                0,
                0,
                1,
                1,
                1,
                0,
                0,
                0
              ]
            },
            "da_reward": {
              "train_total": 26,
              "train_rate": 0.433333,
              "train_last10": 0.6,
              "test_total": 12,
              "test_rate": 0.6,
              "test_last10": 0.5,
              "train_outcomes": [
                0,
                1,
                1,
                0,
                1,
                0,
                0,
                0,
                0,
                1,
                1,
                1,
                0,
                1,
                1,
                0,
                0,
                1,
                0,
                0,
                1,
                0,
                0,
                1,
                0,
                0,
                0,
                0,
                0,
                1,
                0,
                0,
                0,
                1,
                1,
                0,
                1,
                0,
                0,
                0,
                0,
                1,
                0,
                1,
                0,
                1,
                0,
                0,
                1,
                1,
                0,
                1,
                1,
                0,
                1,
                1,
                1,
                0,
                0,
                1
              ],
              "test_outcomes": [
                0,
                1,
                0,
                1,
                1,
                1,
                1,
                1,
                0,
                1,
                1,
                1,
                0,
                0,
                1,
                0,
                1,
                0,
                0,
                1
              ]
            },
            "random": {
              "train_total": 27,
              "train_rate": 0.45,
              "train_last10": 0.3,
              "test_total": 10,
              "test_rate": 0.5,
              "test_last10": 0.4,
              "train_outcomes": [
                0,
                1,
                0,
                1,
                0,
                0,
                1,
                0,
                0,
                1,
                1,
                1,
                0,
                0,
                1,
                1,
                0,
                0,
                0,
                1,
                1,
                0,
                1,
                1,
                0,
                1,
                0,
                0,
                0,
                1,
                0,
                0,
                1,
                1,
                0,
                0,
                1,
                1,
                1,
                0,
                0,
                1,
                0,
                1,
                0,
                1,
                0,
                0,
                1,
                1,
                0,
                0,
                1,
                0,
                0,
                1,
                0,
                0,
                1,
                0
              ],
              "test_outcomes": [
                1,
                0,
                0,
                1,
                1,
                0,
                1,
                1,
                0,
                1,
                0,
                0,
                0,
                0,
                1,
                0,
                1,
                0,
                1,
                1
              ]
            }
          },
          "name": "Pong Signal Optimization"
        }
      }
    },
    {
      "seed": 46,
      "experiments": {
        "6": {
          "passed": false,
          "time": 146.665279,
          "train_rallies": 60,
          "test_rallies": 20,
          "best_signal": "free_energy",
          "results": {
            "free_energy": {
              "train_total": 31,
              "train_rate": 0.516667,
              "train_last10": 0.4,
              "test_total": 12,
              "test_rate": 0.6,
              "test_last10": 0.5,
              "train_outcomes": [
                1,
                0,
                1,
                0,
                0,
                0,
                0,
                0,
                0,
                1,
                1,
                1,
                0,
                1,
                1,
                1,
                1,
                1,
                0,
                0,
                1,
                1,
                1,
                1,
                1,
                1,
                1,
                0,
                0,
                0,
                1,
                0,
                0,
                0,
                0,
                1,
                1,
                0,
                1,
                0,
                1,
                0,
                0,
                1,
                1,
                0,
                1,
                1,
                0,
                1,
                0,
                1,
                0,
                0,
                1,
                1,
                0,
                0,
                1,
                0
              ],
              "test_outcomes": [
                1,
                0,
                1,
                0,
                1,
                1,
                1,
                1,
                0,
                1,
                1,
                0,
                0,
                1,
                1,
                1,
                0,
                0,
                0,
                1
              ]
            },
            "free_energy_balanced": {
              "train_total": 32,
              "train_rate": 0.533333,
              "train_last10": 0.5,
              "test_total": 10,
              "test_rate": 0.5,
              "test_last10": 0.6,
              "train_outcomes": [
                1,
                0,
                1,
                0,
                1,
                0,
                0,
                0,
                0,
                1,
                1,
                1,
                0,
                1,
                0,
                0,
                1,
                1,
                0,
                0,
                1,
                0,
                1,
                1,
                1,
                1,
                1,
                0,
                1,
                0,
                0,
                1,
                0,
                1,
                0,
                1,
                1,
                0,
                1,
                0,
                1,
                0,
                0,
                1,
                1,
                0,
                1,
                0,
                1,
                1,
                0,
                1,
                0,
                1,
                1,
                1,
                0,
                0,
                1,
                0
              ],
              "test_outcomes": [
                1,
                0,
                0,
                0,
                1,
                0,
                1,
                0,
                1,
                0,
                1,
                0,
                1,
                1,
                1,
                1,
                0,
                0,
                0,
                1
              ]
            },
            "free_energy_replay": {
              "train_total": 36,
              "train_rate": 0.6,
              "train_last10": 0.6,
              "test_total": 8,
              "test_rate": 0.4,
              "test_last10": 0.4,
              "train_outcomes": [
                1,
                0,
                1,
                0,
                1,
                0,
                0,
                1,
                0,
                1,
                1,
                1,
                0,
                1,
                1,
                1,
                1,
                1,
                1,
                0,
                1,
                1,
                1,
                0,
                0,
                1,
                1,
                0,
                0,
                0,
                0,
                0,
                1,
                0,
                1,
                1,
                1,
                0,
                1,
                0,
                0,
                1,
                0,
                1,
                1,
                0,
                1,
                1,
                1,
                1,
                0,
                1,
                0,
                1,
                1,
                1,
                0,
                1,
                1,
                0
              ],
              "test_outcomes": [
                0,
                0,
                1,
                0,
                0,
                1,
                0,
                1,
                1,
                0,
                1,
                0,
                0,
                0,
                0,
                1,
                0,
                1,
                0,
                1
              ]
            },
            "free_energy_corrective": {
              "train_total": 25,
              "train_rate": 0.416667,
              "train_last10": 0.3,
              "test_total": 8,
              "test_rate": 0.4,
              "test_last10": 0.1,
              "train_outcomes": [
                1,
                0,
                1,
                0,
                0,
                0,
                0,
                0,
                0,
                1,
                1,
                1,
                0,
                1,
                1,
                1,
                1,
                1,
                0,
                0,
                1,
                0,
                0,
                1,
                1,
                1,
                1,
                0,
                0,
                0,
                0,
                0,
                1,
                0,
                0,
                1,
                1,
                0,
                0,
                0,
                1,
                0,
                0,
                1,
                0,
                0,
                0,
                1,
                1,
                0,
                0,
                1,
                0,
                1,
                0,
                0,
                0,
                0,
                1,
                0
              ],
              "test_outcomes": [
                0,
                1,
                0,
                1,
                1,
                0,
                1,
                1,
                1,
                1,
                1,
                0,
                0,
                0,
                0,
                0,
                0,
                0,
                0,
                0
              ]
            },
            "da_reward": {
              "train_total": 26,
              "train_rate": 0.433333,
              "train_last10": 0.4,
              "test_total": 7,
              "test_rate": 0.35,
              "test_last10": 0.4,
              "train_outcomes": [
                1,
                1,
                1,
                1,
                1,
                0,
                0,
                0,
                0,
                0,
                1,
                1,
                0,
                1,
                0,
                1,
                0,
                0,
                1,
                1,
                1,
                1,
                1,
                0,
                0,
                0,
                0,
                0,
                0,
                1,
                0,
                0,
                0,
                0,
                1,
                1,
                1,
                0,
                1,
                0,
                1,
                0,
                0,
                1,
                1,
                0,
                0,
                0,
                0,
                0,
                0,
                1,
                0,
                1,
                0,
                1,
                0,
                0,
                1,
                0
              ],
              "test_outcomes": [
                0,
                0,
                0,
                0,
                1,
                1,
                0,
                0,
                1,
                0,
                1,
                0,
                1,
                0,
                0,
                1,
                0,
                0,
                0,
                1
              ]
            },
            "random": {
              "train_total": 34,
              "train_rate": 0.566667,
              "train_last10": 0.7,
              "test_total": 9,
              "test_rate": 0.45,
              "test_last10": 0.4,
              "train_outcomes": [
                1,
                1,
                1,
                0,
                0,
                0,
                0,
                0,
                0,
                1,
                0,
                0,
                0,
                1,
                1,
                1,
                0,
                1,
                1,
                1,
                1,
                0,
                1,
                1,
                1,
                1,
                1,
                0,
                0,
                0,
                1,
                0,
                0,
                0,
                1,
                1,
                1,
                1,
                0,
                1,
                1,
                0,
                0,
                1,
                1,
                0,
                1,
                0,
                1,
                0,
                0,
                1,
                1,
                1,
                1,
                1,
                1,
                0,
                1,
                0
              ],
              "test_outcomes": [
                1,
                0,
                0,
                0,
                0,
                1,
                1,
                0,
                1,
                1,
                1,
                0,
                0,
                1,
                1,
                0,
                0,
                0,
                1,
                0
              ]
            }
          },
          "name": "Pong Signal Optimization"
        }
      }
    }
  ]
}