{
  "source_json": "results/pong_compare_20260310/dishbrain_large_a100.json",
  "run_index": 0,
  "seed": 42,
  "experiment": "1",
  "experiment_name": "DishBrain Pong Replication",
  "status": "ok",
  "scale": "large",
  "requested_device": "cuda",
  "platform": "Linux-5.15.0-140-generic-x86_64-with-glibc2.35",
  "python": "3.11.10",
  "torch": "2.5.1+cu124",
  "backend": "cuda",
  "gpu": "NVIDIA A100-SXM4-80GB",
  "gpu_memory_gb": 85.0,
  "passed": true,
  "error": null,
  "assumptions": {
    "dt_ms": 0.1,
    "frames_per_rally": 12,
    "stim_steps": 30,
    "settle_steps": 5,
    "hit_feedback_steps": 50,
    "miss_feedback_steps": 100
  },
  "wall_time_s": 91.886087,
  "rallies": 80,
  "hits": 29,
  "misses": 51,
  "total_hitrate": 0.3625,
  "first_10": 0.1,
  "last_10": 0.6,
  "neural_steps": 40150,
  "bio_time_ms": 4015.0,
  "realtime_factor": 0.043695,
  "slower_than_real_time": 22.8857,
  "rallies_per_s": 0.870643,
  "frames_per_s": 10.447719,
  "neural_steps_per_s": 436.954073,
  "note": "Derived from the fixed Exp 1 Pong loop in demos/demo_dishbrain_pong.py."
}
